[
  { "title": "Train with purpose. Perform at your peak.", "route": "/" },
  { "title": "Contact", "route": "/pages/contact/" },
  { "title": "Memberships", "route": "/pages/memberships/" },
  { "title": "Personal Training", "route": "/pages/personal-training/" },
  { "title": "About CoreActive", "route": "/pages/meet-the-trainers/" },
  { "title": "FAQ", "route": "/pages/faq/" },
  { "title": "Classes", "route": "/pages/classes/" },
  { "title": "UrbanFit", "route": "/pages/rookie/" },
  { "title": "Memberships", "route": "/pages/ballin-fitness-memberships/" },
  { "title": "Memberships", "route": "/pages/group-class-memberships/" },
  { "title": "Kids", "route": "/pages/kids/" },
  { "title": "About CoreActive", "route": "/pages/community/" },
  { "title": "Memberships", "route": "/pages/promo/" },
  { "title": "Schedule", "route": "/pages/schedule/" },
  { "title": "PulseLab", "route": "/pages/hyrox/" },
  { "title": "7-Day Introduction", "route": "/pages/free-trial/" },
  { "title": "Memberships", "route": "/pages/memberships-v2/" },
  { "title": "Credits", "route": "/pages/get-credits/" },
  { "title": "CoreActive Shop", "route": "/collections/frontpage/" },
  { "title": "Memberships Collection", "route": "/collections/memberships/" },
  { "title": "CoreActive Resistance Band Set", "route": "/products/coreactive-resistance-band-set/" },
  { "title": "CoreActive Resistance Band Set", "route": "/products/ballinfit-camo-running-set/" }
]
